<mxfile host="app.diagrams.net" modified="2022-10-21T23:27:58.033Z" agent="5.0 (Macintosh; Intel Mac OS X 10_15_7) AppleWebKit/605.1.15 (KHTML, like Gecko) Version/16.0 Safari/605.1.15" etag="95NZPsvsuuOgEGY0wFHX" version="20.5.0" type="github">
  <diagram id="ygSk8RhbVAYmmRX1YWu_" name="Página-1">
    <mxGraphModel dx="1854" dy="1019" grid="1" gridSize="10" guides="1" tooltips="1" connect="1" arrows="1" fold="1" page="1" pageScale="1" pageWidth="827" pageHeight="1169" math="0" shadow="0">
      <root>
        <mxCell id="0" />
        <mxCell id="1" parent="0" />
        <mxCell id="rBGb2k-MVk60M_Op9p3F-1" value="" style="strokeWidth=1;shadow=0;dashed=0;align=center;html=1;shape=mxgraph.mockup.containers.browserWindow;rSize=0;strokeColor=#1B1E21;strokeColor2=#008cff;strokeColor3=#c4c4c4;mainText=,;recursiveResize=0;fillColor=#FFFFFF;" vertex="1" parent="1">
          <mxGeometry x="100" y="50" width="1160" height="850" as="geometry" />
        </mxCell>
        <mxCell id="rBGb2k-MVk60M_Op9p3F-2" value="MUSEOS" style="strokeWidth=1;shadow=0;dashed=0;align=center;html=1;shape=mxgraph.mockup.containers.anchor;fontSize=14;fontColor=#666666;align=left;" vertex="1" parent="rBGb2k-MVk60M_Op9p3F-1">
          <mxGeometry x="60" y="12" width="110" height="26" as="geometry" />
        </mxCell>
        <mxCell id="rBGb2k-MVk60M_Op9p3F-3" value="https://www.museosdeartemoderno/exhibitions.com.co" style="strokeWidth=1;shadow=0;dashed=0;align=center;html=1;shape=mxgraph.mockup.containers.anchor;rSize=0;fontSize=17;fontColor=#666666;align=left;" vertex="1" parent="rBGb2k-MVk60M_Op9p3F-1">
          <mxGeometry x="130" y="60" width="350" height="20" as="geometry" />
        </mxCell>
        <mxCell id="rBGb2k-MVk60M_Op9p3F-32" value="" style="shape=image;html=1;verticalAlign=top;verticalLabelPosition=bottom;labelBackgroundColor=#ffffff;imageAspect=0;aspect=fixed;image=https://cdn1.iconfinder.com/data/icons/heroicons-solid/20/cursor-click-128.png;strokeColor=#C6C8CA;strokeWidth=1;fontFamily=Helvetica;fontSize=13;fontColor=#66B2FF;" vertex="1" parent="rBGb2k-MVk60M_Op9p3F-1">
          <mxGeometry x="250" y="270" width="50" height="50" as="geometry" />
        </mxCell>
        <mxCell id="rBGb2k-MVk60M_Op9p3F-39" value="Active" style="html=1;shadow=0;dashed=0;shape=mxgraph.bootstrap.tabTop;strokeColor=#DFDFDF;fillColor=#ffffff;rSize=5;perimeter=none;whiteSpace=wrap;resizeWidth=1;align=center;spacing=20;fontSize=14;fontColor=#4B5259;" vertex="1" parent="rBGb2k-MVk60M_Op9p3F-1">
          <mxGeometry x="560" y="130" width="80" height="40" as="geometry" />
        </mxCell>
        <mxCell id="rBGb2k-MVk60M_Op9p3F-40" value="Link" style="strokeColor=none;fillColor=none;rSize=5;perimeter=none;whiteSpace=wrap;resizeWidth=1;align=center;spacing=20;fontSize=14;fontColor=#0085FC;" vertex="1" parent="rBGb2k-MVk60M_Op9p3F-1">
          <mxGeometry x="640" y="130" width="50" height="40" as="geometry" />
        </mxCell>
        <mxCell id="rBGb2k-MVk60M_Op9p3F-41" value="Link" style="strokeColor=none;fillColor=none;rSize=5;perimeter=none;whiteSpace=wrap;resizeWidth=1;align=center;spacing=20;fontSize=14;fontColor=#0085FC;" vertex="1" parent="rBGb2k-MVk60M_Op9p3F-1">
          <mxGeometry x="700" y="130" width="50" height="40" as="geometry" />
        </mxCell>
        <mxCell id="rBGb2k-MVk60M_Op9p3F-42" value="Disabled" style="strokeColor=none;fillColor=none;rSize=5;perimeter=none;whiteSpace=wrap;resizeWidth=1;align=center;spacing=20;fontSize=14;fontColor=#0085FC;fontColor=#4B5259;" vertex="1" parent="rBGb2k-MVk60M_Op9p3F-1">
          <mxGeometry x="750" y="130" width="60" height="40" as="geometry" />
        </mxCell>
        <mxCell id="rBGb2k-MVk60M_Op9p3F-43" value="" style="shape=line;strokeColor=#dddddd;" vertex="1" parent="rBGb2k-MVk60M_Op9p3F-1">
          <mxGeometry x="560" y="180" width="540" height="10" as="geometry" />
        </mxCell>
      </root>
    </mxGraphModel>
  </diagram>
</mxfile>
